{
  "timestamp": "2026-06-22T14:22:43.332Z",
  "summary": {
    "created": 3,
    "updated": 1,
    "deleted": 0
  },
  "created": [
    {
      "branch_code": "05876",
      "name": "Bareta (mansa)",
      "district": "Mansa",
      "state": "Punjab",
      "region": "India"
    },
    {
      "branch_code": "05877",
      "name": "Gurugram Sector 87",
      "district": "Gurugram",
      "state": "Haryana",
      "region": "India"
    },
    {
      "branch_code": "05878",
      "name": "Gorakhpur Taramandal",
      "district": "Gorakhpur",
      "state": "Uttar Pradesh",
      "region": "India"
    }
  ],
  "updated": [
    {
      "branch_code": "04817",
      "name": "Sahibabad Lajpat Nagar",
      "changes": [
        {
          "field": "email",
          "from": null,
          "to": "lajpatnagar.sbb@bkivv.org"
        },
        {
          "field": "mobile",
          "from": "8447595841",
          "to": "8447595841, 7827203922"
        }
      ]
    }
  ],
  "deleted": []
}